mloceanbl/__init__.py
mloceanbl/ann.py
mloceanbl/ann_dropout.py
mloceanbl/data.py
mloceanbl/gp.py
mloceanbl/linear.py
mloceanbl/models.py
mloceanbl/preprocess_mld.py
mloceanbl/preprocess_sss_sst_ssh.py
mloceanbl/train.py
mloceanbl/vae.py
mloceanbl/vann.py
mloceanbl/wget_preprocessed_surface_argo_data.sh
mloceanbl/wget_unprocessed_surface_argo_data.sh
notebooks/__init__.py
notebooks/download_preprocess_data.ipynb
notebooks/mld_spatial_plots.ipynb
notebooks/mld_timeseries_plot.ipynb
notebooks/model_train_example.ipynb
ml_ocean_bl-0.1.dist-info/LICENSE
ml_ocean_bl-0.1.dist-info/METADATA
ml_ocean_bl-0.1.dist-info/WHEEL
ml_ocean_bl-0.1.dist-info/top_level.txt
ml_ocean_bl-0.1.dist-info/RECORD
