Metadata-Version: 2.1
Name: ml-ocean-bl
Version: 0.1
Summary: Machine Learning Ocean Boundary Layer
Home-page: https://github.com/NCAR/ml-ocean-bl
Maintainer: David John Gagne, Dallas Foster, Dan Whitt
Maintainer-email: dgagne@ucar.edu
License: Apache
Keywords: ml-ocean-bl
Platform: UNKNOWN
Requires-Dist: numpy
Requires-Dist: scipy
Requires-Dist: tensorflow
Requires-Dist: tensorflow-probability
Requires-Dist: dask
Requires-Dist: xarray
Requires-Dist: pandas
Requires-Dist: matplotlib
Requires-Dist: jupyter
Requires-Dist: jupyterlab
Requires-Dist: netcdf4
